Bitmasher/__init__.py
Bitmasher/block.py
Bitmasher/crypto.py
Bitmasher/cryptobook.py
Bitmasher/exception.py
Bitmasher/key.py
Bitmasher/next.py
Bitmasher/pass1.py
Bitmasher/pass2.py
Bitmasher/pass3.py
Bitmasher/util.py
Bitmasher-0.0.6.dist-info/LICENSE
Bitmasher-0.0.6.dist-info/METADATA
Bitmasher-0.0.6.dist-info/WHEEL
Bitmasher-0.0.6.dist-info/top_level.txt
Bitmasher-0.0.6.dist-info/RECORD
